{
    "type": "problemSet",
    "title": "python-2-可迭代序列",
    "content": [
        {
            "id": "2033374096656142336",
            "title": "互不相同的数，组成最大整数"
        },
        {
            "id": "2033374096656142337",
            "title": "合法IP"
        },
        {
            "id": "2033375168099483648",
            "title": "《西游记》人物的粉丝数"
        },
        {
            "id": "2033375819353264128",
            "title": "jmu-python-生日悖论"
        },
        {
            "id": "2033375819353264129",
            "title": "jmu-python-班级人员信息统计"
        },
        {
            "id": "2033375819353264130",
            "title": "能被3,5和7整除的数的个数（用集合实现）"
        },
        {
            "id": "2033381955448045568",
            "title": "生成字符地图的子地图"
        },
        {
            "id": "2033381955448045569",
            "title": "第几天"
        }
    ]
}