{
    "title": "Python-1-基础",
    "id": "2030646312838070272",
    "content": [
        {
            "title": "付钱方案",
            "id": "2030648800869842944",
            "proid": "7-1"
        },
        {
            "title": "读数字",
            "id": "2030648800869842945",
            "proid": "7-2"
        },
        {
            "title": "汉明距离",
            "id": "2030648800869842947",
            "proid": "7-3"
        },
        {
            "title": "优秀的拆分",
            "id": "2030651067396227072",
            "proid": "7-4"
        },
        {
            "title": "时光流逝",
            "id": "2030651067396227073",
            "proid": "7-5"
        },
        {
            "title": "随机输出字符串",
            "id": "2030651067396227074",
            "proid": "7-6"
        }
    ]
}