{
    "type": "problem",
    "title": "三国演义中文分词与词频统计",
    "content": [
        {
            "code": "import jieba\nimport sys\n\nnames = [\"曹操\", \"刘备\", \"孙权\", \"诸葛亮\", \"孔明\", \"关羽\", \"云长\", \"张飞\", \"翼德\", \"赵云\", \"子龙\", \"马超\", \"孟起\", \"黄忠\", \"汉升\", \"周瑜\", \"公瑾\",\"吕布\",\"玄德\", \"华雄\", \"颜良\", \"文丑\", \"周郎\", \"仲谋\", \"许褚\", \"夏侯渊\"]\n\ncnt = {}\n\nwords = jieba.lcut(sys.stdin.read())\n\nfor word in words:\n    if word in names:\n        cnt[word] = cnt.get(word, 0) + 1\n\nfor i,j in cnt.items():\n    print(f\"{i}: {j}\")\n",
            "language": "python"
        }
    ],
    "description": "请编写一个Python程序，对《三国演义》的部分内容进行中文分词，并统计词频（不排序）。\nnames = {\n \"曹操\", \"刘备\", \"孙权\", \"诸葛亮\", \"孔明\", \"关羽\", \"云长\", \"张飞\", \"翼德\", \"赵云\", \"子龙\", \"马超\", \"孟起\", \"黄忠\", \"汉升\", \"周瑜\", \"公瑾\",\"吕布\",\"玄德\", \"华雄\", \"颜良\", \"文丑\", \"周郎\", \"仲谋\", \"许褚\", \"夏侯渊\"\n }\n中文分词：\nimport jieba\nwords = jieba.lcut()\n\n### 输入格式:\n\n程序将接收一个包含《三国演义》片段的一段文本\n\n### 输出格式:\n\n词频统计结果\n\n### 输入样例:\n\n在这里给出一组输入。例如：\n\n```in\n\"\"\"却说曹操引军自京师迎帝许都，自此大权皆归于曹操。玄德到寓，星夜收拾军器鞍马，挂了将军印，催促便行。孔明在荆州，闻知曹操已死，遂入川劝玄德即位。云长提华雄头，掷于地上，其酒尚温。周瑜急急下得船时，岸上军士齐声大叫曰：周郎妙计安天下，赔了夫人又折兵！\"\"\"\n```\n\n### 输出样例:\n\n\n```out\n曹操: 2\n孔明: 1\n周瑜: 1\n周郎: 1\n```\n"
}